pixelkit/__init__.py
pixelkit-0.0.1a1.dist-info/METADATA
pixelkit-0.0.1a1.dist-info/WHEEL
pixelkit-0.0.1a1.dist-info/licenses/LICENSE
pixelkit-0.0.1a1.dist-info/RECORD
